{
    "patients": [
      {
        "id": 1532,
        "Paciente": "Javier Andrés Caicedo Rodriguez",
        "Identificacion": "1234567894",
        "Celular": "302415234",
        "Entidad": "Eps Sanitas",
        "Ultima Atencion": "10/01/2024",
        "Tipo de Atencion": "Psicologia",
        "Estado": "Estable",
        "Fecha Nacimiento": "01/01/1992",
        "Edad": "32",
        "Tipo de Identificacion": "Cedula de Cuidadania",
        "Telefono": "(58) 1243532",
        "Direccion": "Calle 15C # 92-51",
        "Ocupacion": "Independiente",
        "Observacion": "El paciente presenta mejoras, cada día es mas consiente de lo sucedido días previos a su consulta",
        "Checkin": "2/7/2025 8:26"
      },
      {
        "id": 1533,
        "Paciente": "Ana María González López",
        "Identificacion": "987654321",
        "Celular": "3115678932",
        "Entidad": "Eps Sura",
        "Ultima Atencion": "12/02/2024",
        "Tipo de Atencion": "Psiquiatría",
        "Estado": "Critico",
        "Fecha Nacimiento": "15/05/1987",
        "Edad": "48",
        "Tipo de Identificacion": "Cédula de Ciudadanía",
        "Telefono": "(602) 7654321",
        "Direccion": "Carrera 10 # 20-15",
        "Ocupacion": "Docente",
        "Observacion": "Necesita estar con su familia ",
        "Checkin": "2/7/2025 8:47"
      },
      {
        "id": 1534,
        "Paciente": "Carlos Alberto Mendoza Pérez",
        "Identificacion": "456789123",
        "Celular": "3206541237",
        "Entidad": "Nueva EPS",
        "Ultima Atencion": "08/03/2024",
        "Tipo de Atencion": "Psicología",
        "Estado": "Moderado",
        "Fecha Nacimiento": "22/09/1990",
        "Edad": 34,
        "Tipo de Identificacion": "Cédula de Ciudadanía",
        "Telefono": "(601) 3332221",
        "Direccion": "Av. Siempre Viva 123",
        "Ocupacion": "Ingeniero",
        "Observacion": "Necesita mas cuidado ya que puede estar presentando problemas ",
        "Checkin": "2/6/2025 16:20"
      },
      {
        "id": 1535,
        "Paciente": "Mariana Fernadez Torres Salazar",
        "Identificacion": "159753468",
        "Celular": "305753246",
        "Entidad": "Eps Coomeva",
        "Ultima Atencion": "05/04/2024",
        "Tipo de Atencion": "Psiquiatría",
        "Estado": "Estable",
        "Fecha Nacimiento": "10/07/1995",
        "Edad": "24",
        "Tipo de Identificacion": "Cédula de Ciudadanía",
        "Telefono": "(604) 9988776",
        "Direccion": "Calle 8 # 50-20",
        "Ocupacion": "Administradora",
        "Checkin": "2/6/2025 16:39",
        "Observacion": "Tendra salida pronto si mejora"
      },
      {
        "id": 1536,
        "Paciente": "Luis Fernando Castro Ramírez",
        "Identificacion": "357159246532",
        "Celular": "31234567890",
        "Entidad": "Eps Famisanar",
        "Ultima Atencion": "15/04/2024",
        "Tipo de Atencion": "Psicología",
        "Estado": "Estable",
        "Fecha Nacimiento": "20/12/1985",
        "Edad": "31",
        "Tipo de Identificacion": "Cédula de Ciudadanía",
        "Telefono": "(57) 123456732",
        "Direccion": "Transversal 45 # 30-80",
        "Ocupacion": "Contador",
        "Observacion": "este saleeee",
        "Checkin": "2/7/2025 8:33"
      },
      {
        "id": 1537,
        "Paciente": "Pedro José Pérez González",
        "Identificacion": "1122334455",
        "Celular": "3131234567",
        "Entidad": "Eps Sanitas",
        "Ultima Atencion": "20/01/2024",
        "Tipo de Atencion": "Psicologia",
        "Estado": "Estable",
        "Fecha Nacimiento": "30/03/1980",
        "Edad": "44",
        "Tipo de Identificacion": "Cédula de Ciudadanía",
        "Telefono": "(602) 1234567",
        "Direccion": "Calle 10 # 30-60",
        "Ocupacion": "Arquitecto",
        "Observacion": "Paciente con buena recuperación",
        "Checkin": "2/7/2025 9:15"
      },
      {
        "id": 1538,
        "Paciente": "Marta Lucía Rodríguez Gómez",
        "Identificacion": "9988776655",
        "Celular": "3127654321",
        "Entidad": "Eps Sura",
        "Ultima Atencion": "18/02/2024",
        "Tipo de Atencion": "Psicología",
        "Estado": "Moderado",
        "Fecha Nacimiento": "05/08/1975",
        "Edad": "49",
        "Tipo de Identificacion": "Cédula de Ciudadanía",
        "Telefono": "(601) 7896543",
        "Direccion": "Calle 12 # 56-78",
        "Ocupacion": "Contadora",
        "Observacion": "Necesita seguimiento constante",
        "Checkin": "2/7/2025 9:45"
      },
      {
        "id": 1539,
        "Paciente": "Luis Miguel Gómez Sánchez",
        "Identificacion": "123987654",
        "Celular": "3212345678",
        "Entidad": "Eps Coomeva",
        "Ultima Atencion": "02/03/2024",
        "Tipo de Atencion": "Neurología",
        "Estado": "Estable",
        "Fecha Nacimiento": "12/11/1992",
        "Edad": "32",
        "Tipo de Identificacion": "Cédula de Ciudadanía",
        "Telefono": "(607) 6543210",
        "Direccion": "Carrera 8 # 45-30",
        "Ocupacion": "Psicólogo",
        "Observacion": "Está en tratamiento de rehabilitación",
        "Checkin": "2/7/2025 10:00"
      },
      {
        "id": 1540,
        "Paciente": "Isabel Cristina Gómez Sánchez",
        "Identificacion": "456123789",
        "Celular": "3109876543",
        "Entidad": "Eps Famisanar",
        "Ultima Atencion": "10/03/2024",
        "Tipo de Atencion": "Psiquiatría",
        "Estado": "Critico",
        "Fecha Nacimiento": "22/01/1980",
        "Edad": "44",
        "Tipo de Identificacion": "Cédula de Ciudadanía",
        "Telefono": "(609) 5432109",
        "Direccion": "Calle 14 # 75-20",
        "Ocupacion": "Médica",
        "Observacion": "Requiere cirugía urgente",
        "Checkin": "2/7/2025 10:15"
      },
      {
        "id": 1541,
        "Paciente": "Andrés Felipe Soto Pérez",
        "Identificacion": "9987654321",
        "Celular": "3146549876",
        "Entidad": "Eps Nueva EPS",
        "Ultima Atencion": "30/03/2024",
        "Tipo de Atencion": "Psiquiatría",
        "Estado": "Critico",
        "Fecha Nacimiento": "10/10/1978",
        "Edad": "46",
        "Tipo de Identificacion": "Cédula de Ciudadanía",
        "Telefono": "(600) 2223344",
        "Direccion": "Calle 20 # 10-35",
        "Ocupacion": "Abogado",
        "Observacion": "Estado de salud muy delicado",
        "Checkin": "2/7/2025 10:30"
      }
    ]
  }
  